MANIFEST.in
README.rst
setup.cfg
setup.py
etc/default/greins
etc/init/greins
greins/__init__.py
greins/app.py
greins/reloader.py
greins/router.py
greins/synchronization.py
greins.egg-info/PKG-INFO
greins.egg-info/SOURCES.txt
greins.egg-info/dependency_links.txt
greins.egg-info/entry_points.txt
greins.egg-info/not-zip-safe
greins.egg-info/requires.txt
greins.egg-info/top_level.txt