Metadata-Version: 1.0
Name: greins
Version: 0.2.0
Summary: Greins is tack for Gunicorn.
Home-page: http://github.com/meebo/greins
Author: Randall Leeds
Author-email: randall@meebo-inc.com
License: MIT License
Platform: UNKNOWN
Classifier: Development Status :: 4 - Beta
Classifier: Environment :: Other Environment
Classifier: Intended Audience :: Developers
Classifier: License :: OSI Approved :: MIT License
Classifier: Operating System :: POSIX
Classifier: Programming Language :: Python
Classifier: Topic :: Internet
Classifier: Topic :: Utilities
Classifier: Topic :: Software Development :: Libraries :: Python Modules
